fastasplit/__init__.py
fastasplit/fastasplit.py
fastasplit/version.py
fastasplit-1.3.1.dist-info/LICENSE
fastasplit-1.3.1.dist-info/METADATA
fastasplit-1.3.1.dist-info/WHEEL
fastasplit-1.3.1.dist-info/entry_points.txt
fastasplit-1.3.1.dist-info/top_level.txt
fastasplit-1.3.1.dist-info/RECORD
