Metadata-Version: 2.1
Name: fastasplit
Version: 1.3.1
Summary: Split fasta files
Home-page: https://github.com/jtompkin/fastasplit
Author: Josh Tompkin
Author-email: tompkinjo@gmail.com
License: GPLv3
Project-URL: Changelog, https://github.com/jtompkin/fastasplit/blob/main/CHANGELOG.md
Classifier: Programming Language :: Python :: 3
Classifier: License :: OSI Approved :: GNU General Public License v3 (GPLv3)
Requires-Python: >=3.7
License-File: LICENSE
